jaeger_logger_reporter/__init__.py
jaeger_logger_reporter/config.py
jaeger_logger_reporter/reporter.py
jaeger_logger_reporter-0.0.7.dist-info/LICENSE
jaeger_logger_reporter-0.0.7.dist-info/METADATA
jaeger_logger_reporter-0.0.7.dist-info/WHEEL
jaeger_logger_reporter-0.0.7.dist-info/top_level.txt
jaeger_logger_reporter-0.0.7.dist-info/RECORD
