Metadata-Version: 2.1
Name: jaeger-logger-reporter
Version: 0.0.7
Summary: Jaeger Logger Reporter
Home-page: https://github.com/cristianoalves92/jaeger_logger_reporter
Author: Cristiano Alves
Author-email: cristiano.f.t.alves@gmail.com
License: UNKNOWN
Platform: UNKNOWN
Classifier: Programming Language :: Python :: 3.7
Classifier: License :: OSI Approved :: Apache Software License
Requires-Dist: jaeger-client (>=4.3.0)
Requires-Dist: opentracing (>=2.3.0)
